mixer/__main__.py
aya_mixer-1.0.0.dist-info/METADATA
aya_mixer-1.0.0.dist-info/WHEEL
aya_mixer-1.0.0.dist-info/entry_points.txt
aya_mixer-1.0.0.dist-info/top_level.txt
aya_mixer-1.0.0.dist-info/RECORD
