Metadata-Version: 2.1
Name: aya-mixer
Version: 1.0.0
Summary: mixing high school tests
Author-email: Chi <chinguyen.dev@gmail.com>
Project-URL: Homepage, https://github.com/ayaderaghul/mixer
Keywords: mix,test
Classifier: License :: OSI Approved :: MIT License
Classifier: Programming Language :: Python
Classifier: Programming Language :: Python :: 3
Requires-Python: >=3.9
Requires-Dist: beautifulsoup4
Provides-Extra: dev
Requires-Dist: pytest ; extra == 'dev'
